rpm_spec_language_server/__init__.py
rpm_spec_language_server/__main__.py
rpm_spec_language_server/document_symbols.py
rpm_spec_language_server/extract_docs.py
rpm_spec_language_server/logging.py
rpm_spec_language_server/macros.py
rpm_spec_language_server/main.py
rpm_spec_language_server/server.py
rpm_spec_language_server/util.py
rpm_spec_language_server-0.0.2.dist-info/METADATA
rpm_spec_language_server-0.0.2.dist-info/WHEEL
rpm_spec_language_server-0.0.2.dist-info/entry_points.txt
rpm_spec_language_server-0.0.2.dist-info/licenses/LICENSE
rpm_spec_language_server-0.0.2.dist-info/RECORD
