Metadata-Version: 2.4
Name: rpm_spec_language_server
Version: 0.0.2
Summary: Language Server for RPM spec files
License: GPL-2.0-or-later
License-File: LICENSE
Author: Dan Čermák
Author-email: dcermak@suse.com
Requires-Python: >=3.9,<4.0
Classifier: License :: OSI Approved :: GNU General Public License v2 or later (GPLv2+)
Classifier: Programming Language :: Python :: 3
Classifier: Programming Language :: Python :: 3.9
Classifier: Programming Language :: Python :: 3.10
Classifier: Programming Language :: Python :: 3.11
Classifier: Programming Language :: Python :: 3.12
Classifier: Programming Language :: Python :: 3.13
Classifier: Programming Language :: Python :: 3.14
Requires-Dist: pygls (>=2.0,<3.0)
Requires-Dist: requests (>=2.32)
Requires-Dist: rpm (>=0.2.0)
Requires-Dist: specfile (>=0.18)
